docs/__init__.py
docs/conf.py
docs/index.rst
docs/summary.rst
docs/likegeeks_tutorial/__init__.py
docs/likegeeks_tutorial/md_to_html.py
docs/likegeeks_tutorial/tutorial.md
docs/likegeeks_tutorial/tutorial.rst
docs/likegeeks_tutorial/code/__init__.py
docs/likegeeks_tutorial/code/button.py
docs/likegeeks_tutorial/code/change_colours.py
docs/likegeeks_tutorial/code/combobox.py
docs/likegeeks_tutorial/code/disable_entry_widget.py
docs/likegeeks_tutorial/code/get_radiobutton_value.py
docs/likegeeks_tutorial/code/handle_button_clicked_event.py
docs/likegeeks_tutorial/code/int_radiobutton.py
docs/likegeeks_tutorial/code/label.py
docs/likegeeks_tutorial/code/radiobox.py
docs/likegeeks_tutorial/code/radiobox_dict_options.py
docs/likegeeks_tutorial/code/radiobutton.py
docs/likegeeks_tutorial/code/set_label_font_size.py
docs/likegeeks_tutorial/code/set_read_the_state_of_a_switch.py
docs/likegeeks_tutorial/code/set_window_size.py
docs/likegeeks_tutorial/code/standalone.py
docs/likegeeks_tutorial/code/switch.py
docs/likegeeks_tutorial/code/switchbox.py
docs/likegeeks_tutorial/code/switchbox_dictionary_switches.py
docs/likegeeks_tutorial/code/textentry.py
docs/likegeeks_tutorial/code/textscroll.py
docs/likegeeks_tutorial/code/tutorial_4_1_add_a_text_entry_widget.py
docs/likegeeks_tutorial/code/value_mapped_combobox.py
docs/styles/__init__.py
docs/styles/button_styles.py
docs/widgets_and_dialogs/__init__.py
docs/widgets_and_dialogs/button/__init__.py
docs/widgets_and_dialogs/calendar/__init__.py
docs/widgets_and_dialogs/combobox/__init__.py
docs/widgets_and_dialogs/entry/__init__.py
docs/widgets_and_dialogs/label/__init__.py
docs/widgets_and_dialogs/query/__init__.py
docs/widgets_and_dialogs/radiobox/__init__.py
docs/widgets_and_dialogs/radiobutton/__init__.py
docs/widgets_and_dialogs/scroll/__init__.py
docs/widgets_and_dialogs/separator/__init__.py
docs/widgets_and_dialogs/spinbox/__init__.py
docs/widgets_and_dialogs/switch/__init__.py
uiutil-1.38.0.dist-info/LICENSE.txt
uiutil-1.38.0.dist-info/METADATA
uiutil-1.38.0.dist-info/WHEEL
uiutil-1.38.0.dist-info/entry_points.txt
uiutil-1.38.0.dist-info/top_level.txt
uiutil-1.38.0.dist-info/RECORD
