Metadata-Version: 2.1
Name: uiutil
Version: 1.38.0
Summary: Utility module to assist creating Tk GUIs.
Home-page: https://bitbucket.org/davisowb/owbd-python-module-template.git
Author: Oli Davis & Hywel Thomas
Author-email: oli.davis@me.com, hywel.thomas@mac.com
License: MIT
Download-URL: https://bitbucket.org/davisowb/owbd-python-module-template.git/get/1.38.0.tar
Keywords: uiutil
Platform: UNKNOWN
Classifier: Development Status :: 3 - Alpha
Classifier: Intended Audience :: Developers
Classifier: License :: OSI Approved :: MIT License
Classifier: Programming Language :: Python :: 2
Classifier: Programming Language :: Python :: 2.7
Classifier: Programming Language :: Python :: 3
Classifier: Programming Language :: Python :: 3.6
Classifier: Topic :: Utilities
License-File: LICENSE.txt
Requires-Dist: pip (>=18.1)
Requires-Dist: future (>=0.16.0attrs>=16.3.0)
Requires-Dist: logging-helper (>=1.8.2)
Requires-Dist: stateutil (>=1.4.0)
Requires-Dist: classutils (>=1.18.0)
Requires-Dist: configurationutil (>=1.5.6)
Requires-Dist: fdutil (>=1.7.8)
Requires-Dist: Pillow (>=4.0.0)
Requires-Dist: conversionutil (>=1.4.1)
Requires-Dist: timingsutil (>=1.5.0)
Provides-Extra: test
